ip3country/__init__.py
ip3country/country_lookup.py
ip3country/country_lookup_test.py
ip3country/data/ip_supalite.table
ip3country-0.4.0.dist-info/LICENSE
ip3country-0.4.0.dist-info/METADATA
ip3country-0.4.0.dist-info/WHEEL
ip3country-0.4.0.dist-info/top_level.txt
ip3country-0.4.0.dist-info/RECORD
